{
    "latency": {
        "simple": {
            "bincode": {
                "2": 2.3225767,
                "4": 2.3360114999999997,
                "8": 2.33369565,
                "16": 2.5247363999999997,
                "32": 2.544399125,
                "64": 2.7202667750000002,
                "128": 2.8813045749999997,
                "256": 3.0432384,
                "512": 3.3066406749999997,
                "1024": 3.9761627,
                "2048": 4.824326675,
                "4096": 6.469632024999999,
                "8192": 9.07200525,
                "16384": 16.58679175,
                "32768": 30.9117465,
                "65536": 50.3516485
            },
            "iovec": {
                "2": 2.3074654249999997,
                "4": 2.280091525,
                "8": 2.2953195749999997,
                "16": 2.479496225,
                "32": 2.54671905,
                "64": 2.761219675,
                "128": 2.945294425,
                "256": 3.1534323,
                "512": 3.4042816,
                "1024": 4.022293325,
                "2048": 4.5628161,
                "4096": 5.761057975000001,
                "8192": 7.454132475000001,
                "16384": 10.8813905,
                "32768": 21.046838,
                "65536": 33.217057249999996
            },
            "rsmpi": {
                "2": 0.244511585,
                "4": 0.2618702,
                "8": 0.2596094775,
                "16": 0.27984383,
                "32": 0.3746886875,
                "64": 0.2733651325,
                "128": 0.3443535675,
                "256": 0.3527461325,
                "512": 0.38043943,
                "1024": 0.4112821725,
                "2048": 0.5107460825,
                "4096": 0.62796,
                "8192": 0.860885765,
                "16384": 1.2314609250000002,
                "32768": 1.88300785,
                "65536": 3.181328725
            }
        },
        "complex-noncompound": {
            "bincode": {
                "2048": 5.7921005249999995,
                "4096": 8.51535675,
                "8192": 12.9164455,
                "16384": 21.421381250000003,
                "32768": 44.332881,
                "65536": 79.24445175
            },
            "iovec": {
                "2048": 4.840829,
                "4096": 6.474912399999999,
                "8192": 8.5408245,
                "16384": 12.44967675,
                "32768": 23.403181749999998,
                "65536": 37.1327485
            },
            "rsmpi": {
                "2048": 2.3050867000000004,
                "4096": 4.00355255,
                "8192": 7.4001659,
                "16384": 11.2830545,
                "32768": 18.512204750000002,
                "65536": 34.30030024999999
            }
        },
        "complex-compound": {
            "bincode": {
                "128": 2.308714675,
                "256": 2.31135815,
                "512": 2.3158054,
                "1024": 2.313759625,
                "2048": 3.949221225,
                "4096": 6.193886299999999,
                "8192": 9.39258725,
                "16384": 16.7494655,
                "32768": 33.5779195,
                "65536": 55.20184474999999,
                "131072": 132.56545250000002
            },
            "iovec": {
                "128": 2.3159951,
                "256": 2.319254375,
                "512": 2.3096586,
                "1024": 2.316079,
                "2048": 3.8834446999999996,
                "4096": 6.3368523,
                "8192": 11.035632375,
                "16384": 19.30390525,
                "32768": 41.53085625000001,
                "65536": 73.89939875,
                "131072": 135.702695
            }
        }
    },
    "bw": {
        "complex-noncompound": {
            "iovec": {
                "2048": 807.5184125000001,
                "4096": 1092.405525,
                "8192": 1287.7383,
                "16384": 1447.5465,
                "32768": 650.55111,
                "65536": 953.24715
            },
            "bincode": {
                "2048": 1339.730075,
                "4096": 993.9504925,
                "8192": 1708.33065,
                "16384": 2033.1276,
                "32768": 1583.0270999999998,
                "65536": 1146.326175
            },
            "flat": {
                "2048": 1679.404975,
                "4096": 3004.610125,
                "8192": 246.81363125000001,
                "16384": 89.81738949999999,
                "32768": 6555.078975,
                "65536": 7289.7076
            },
            "rsmpi": {
                "2048": 1826.541625,
                "4096": 1952.850075,
                "8192": 2044.9473750000002,
                "16384": 2123.735475,
                "32768": 2150.74865,
                "65536": 2150.525075
            }
        },
        "complex-compound": {
            "iovec": {
                "128": 106.863676,
                "256": 212.91881,
                "512": 426.67807,
                "1024": 853.18915,
                "2048": 1093.7811499999998,
                "4096": 1111.1123499999999,
                "8192": 1087.6644250000002,
                "16384": 988.894975,
                "32768": 579.4008125,
                "65536": 759.100135,
                "131072": 872.2619574999999
            },
            "bincode": {
                "128": 125.62201750000001,
                "256": 251.860855,
                "512": 503.9456125,
                "1024": 1003.83124,
                "2048": 1490.4515250000002,
                "4096": 879.5007549999999,
                "8192": 1748.1618,
                "16384": 1261.76035,
                "32768": 1488.11445,
                "65536": 1414.2096999999999,
                "131072": 2782.600875
            }
        }
    }
}